{"is_source_file": true, "file_id": 25, "git_revision": "", "state": 1, "description": "", "external_files": [], "external_methods": [], "published": [], "classes": [], "methods": [], "calls": [], "search-terms": [], "ctags": [{"_type": "tag", "name": "NavigationBar", "path": "/home/kavia/workspace/code-generation/todo-list-manager-0c3f8865/todos_frontend/src/components/NavigationBar.jsx", "pattern": "/^const NavigationBar = () => {$/", "language": "JavaScript", "kind": "constant"}], "format": "JavaScript", "hash": "6b667248c96c7856a416b880a568f34d", "format-version": 4, "code-base-name": "todos_frontend", "filename": "todos_frontend/src/components/NavigationBar.jsx", "knowledge_revision": 48}